dynamic_config/__init__.py
dynamic_config/dynamic_config.py
dynamic_config-0.1.0.dist-info/LICENSE
dynamic_config-0.1.0.dist-info/LICENSE.md
dynamic_config-0.1.0.dist-info/WHEEL
dynamic_config-0.1.0.dist-info/METADATA
dynamic_config-0.1.0.dist-info/RECORD
