Metadata-Version: 2.1
Name: dynamic-config
Version: 0.1.0
Summary: Distributed dynamic configuration based on Redis
Home-page: https://github.com/Euraxluo/dynamic_config
License: The MIT LICENSE
Author: Euraxluo
Author-email: euraxluo@qq.com
Requires-Python: >=3.6.5,<4.0.0
Classifier: License :: Other/Proprietary License
Classifier: Programming Language :: Python :: 3
Classifier: Programming Language :: Python :: 3.10
Classifier: Programming Language :: Python :: 3.7
Classifier: Programming Language :: Python :: 3.8
Classifier: Programming Language :: Python :: 3.9
Requires-Dist: redis (>=4.1.4,<5.0.0)
Project-URL: Repository, https://github.com/Euraxluo/dynamic_config
